cascading_rainbow/__init__.py
cascading_rainbow/rainbow.py
cascading_rainbow-0.0.1.dist-info/METADATA
cascading_rainbow-0.0.1.dist-info/WHEEL
cascading_rainbow-0.0.1.dist-info/top_level.txt
cascading_rainbow-0.0.1.dist-info/RECORD
