Metadata-Version: 2.1
Name: cascading-rainbow
Version: 0.0.1
Summary: Custom rainbow powerline segments!
Home-page: https://github.com/soybean/cascading-rainbow-powerline
Author: Mel Sawyer
Author-email: melanie.sawyer@columbia.edu
License: MIT
Platform: UNKNOWN
